{
  "setting": {
    "packNpmManually": true,
    "packNpmRelationList": [
      {
        "packageJsonPath": "./package.json",
        "miniprogramNpmDistDir": "/node_modules/"
      }
    ]
  },
  "condition": {
    "plugin": {
      "list": []
    },
    "game": {
      "list": []
    },
    "gamePlugin": {
      "list": []
    },
    "miniprogram": {
      "list": [
        {
          "name": "服务",
          "pathName": "pages/service/service",
          "query": "",
          "scene": null,
          "partialCompile": {
            "enabled": true,
            "pages": [
              "pages/service/service"
            ]
          }
        },
        {
          "name": "我的",
          "pathName": "pages/mine/mine",
          "query": "",
          "scene": null,
          "partialCompile": {
            "enabled": true,
            "pages": []
          }
        },
        {
          "name": "垃圾信息",
          "pathName": "pages/indexs/garbage/garbage",
          "query": "",
          "scene": null,
          "partialCompile": {
            "enabled": true,
            "pages": []
          }
        },
        {
          "name": "热门资讯",
          "pathName": "pages/packageService/pages/services/wikis/wiki/wiki",
          "query": "",
          "scene": null
        },
        {
          "name": "资讯详情",
          "pathName": "pages/packageService/pages/services/wikis/wikiinfo/wikiinfo",
          "query": "id=2",
          "scene": null,
          "partialCompile": {
            "enabled": true,
            "pages": []
          }
        },
        {
          "name": "游戏专区",
          "pathName": "pages/services/games/game/game",
          "query": "",
          "scene": null,
          "partialCompile": {
            "enabled": true,
            "pages": []
          }
        },
        {
          "name": "拍照打卡",
          "pathName": "pages/services/pictuclocks/pictuclock/pictuclock",
          "query": "",
          "scene": null,
          "partialCompile": {
            "enabled": true,
            "pages": []
          }
        },
        {
          "name": "每日打卡",
          "pathName": "pages/services/pictuclocks/pictuclockadd/pictuclockadd",
          "query": "",
          "scene": null,
          "partialCompile": {
            "enabled": true,
            "pages": []
          }
        },
        {
          "name": "公益视频",
          "pathName": "pages/services/welfvideos/welfvideo/welfvideo",
          "query": "",
          "scene": null,
          "partialCompile": {
            "enabled": true,
            "pages": []
          }
        },
        {
          "name": "视频详情",
          "pathName": "pages/services/welfvideos/welfvideoinfo/welfvideoinfo",
          "query": "",
          "scene": null,
          "partialCompile": {
            "enabled": true,
            "pages": []
          }
        },
        {
          "name": "我的收藏",
          "pathName": "pages/packageService/pages/services/collects/collect/collect",
          "query": "",
          "scene": null,
          "partialCompile": {
            "enabled": true,
            "pages": []
          }
        },
        {
          "name": "变废为宝",
          "pathName": "pages/packageService/pages/services/wastetreas/wastetrea/wastetrea",
          "query": "",
          "scene": null,
          "partialCompile": {
            "enabled": true,
            "pages": []
          }
        },
        {
          "name": "变废为宝视频详情",
          "pathName": "pages/services/wastetreas/wastetreainfo/wastetreainfo",
          "query": "id=0",
          "scene": null,
          "partialCompile": {
            "enabled": true,
            "pages": []
          }
        },
        {
          "name": "变废为宝(我的)",
          "pathName": "pages/packageService/pages/services/wastetreas/wastetreamy/wastetreamy",
          "query": "",
          "scene": null,
          "partialCompile": {
            "enabled": true,
            "pages": []
          }
        },
        {
          "name": "变废为宝(收藏)",
          "pathName": "pages/packageService/pages/services/wastetreas/wastetreacollect/wastetreacollect",
          "query": "",
          "scene": null,
          "partialCompile": {
            "enabled": true,
            "pages": []
          }
        },
        {
          "name": "变废为宝(发布)",
          "pathName": "pages/packageService/pages/services/wastetreas/wastetreapublish/wastetreapublish",
          "query": "",
          "scene": null,
          "partialCompile": {
            "enabled": true,
            "pages": []
          }
        },
        {
          "name": "政策宣传",
          "pathName": "pages/packageService/pages/services/policydocs/policydoc/policydoc",
          "query": "",
          "scene": null,
          "partialCompile": {
            "enabled": true,
            "pages": []
          }
        },
        {
          "name": "志愿招募",
          "pathName": "pages/services/activitys/activity/activity",
          "query": "",
          "scene": null,
          "partialCompile": {
            "enabled": true,
            "pages": []
          }
        },
        {
          "name": "招募详情",
          "pathName": "pages/services/activitys/activityinfo/activityinfo",
          "query": "",
          "scene": null,
          "partialCompile": {
            "enabled": true,
            "pages": []
          }
        },
        {
          "name": "政策详情",
          "pathName": "pages/packageService/pages/services/policydocs/policydocinfo/policydocinfo",
          "query": "",
          "scene": null,
          "partialCompile": {
            "enabled": true,
            "pages": []
          }
        },
        {
          "name": "积分说明",
          "pathName": "pages/mines/integdescs/integdesc/integdesc",
          "query": "",
          "scene": null,
          "partialCompile": {
            "enabled": true,
            "pages": []
          }
        },
        {
          "name": "积分记录",
          "pathName": "pages/mines/integlogs/integlog/integlog",
          "query": "",
          "scene": null,
          "partialCompile": {
            "enabled": true,
            "pages": []
          }
        },
        {
          "name": "积分等级",
          "pathName": "pages/mines/integlevels/integlevel/integlevel",
          "query": "",
          "scene": null,
          "partialCompile": {
            "enabled": true,
            "pages": []
          }
        },
        {
          "name": "积分排名",
          "pathName": "pages/mines/integranks/integrank/integrank",
          "query": "",
          "scene": null,
          "partialCompile": {
            "enabled": true,
            "pages": []
          }
        },
        {
          "name": "关于我们",
          "pathName": "pages/mines/myabouts/myabout/myabout",
          "query": "",
          "scene": null,
          "partialCompile": {
            "enabled": true,
            "pages": []
          }
        },
        {
          "name": "积分兑换",
          "pathName": "pages/mines/integexcuhs/integexcuh/integexcuh",
          "query": "",
          "scene": null,
          "partialCompile": {
            "enabled": true,
            "pages": []
          }
        },
        {
          "name": "知识测试",
          "pathName": "pages/packageService/pages/services/knowtests/knowtest/knowtest",
          "query": "",
          "scene": null,
          "partialCompile": {
            "enabled": true,
            "pages": []
          }
        },
        {
          "name": "答题规则",
          "pathName": "pages/packageService/pages/services/knowtests/testrules/testrules",
          "query": "",
          "scene": null,
          "partialCompile": {
            "enabled": true,
            "pages": []
          }
        },
        {
          "name": "每日答题",
          "pathName": "pages/packageService/pages/services/knowtests/answereveryday/answereveryday",
          "query": "",
          "scene": null,
          "partialCompile": {
            "enabled": true,
            "pages": []
          }
        },
        {
          "name": "答题历史",
          "pathName": "pages/packageService/pages/services/knowtests/testhistory/testhistory",
          "query": "",
          "scene": null,
          "partialCompile": {
            "enabled": true,
            "pages": []
          }
        },
        {
          "name": "分类小考",
          "pathName": "pages/packageService/pages/services/knowtests/classquiz/classquiz",
          "query": "",
          "scene": null,
          "partialCompile": {
            "enabled": true,
            "pages": []
          }
        },
        {
          "name": "订单记录",
          "pathName": "pages/mines/myorders/myorder/myorder",
          "query": "",
          "scene": null,
          "partialCompile": {
            "enabled": true,
            "pages": []
          }
        },
        {
          "name": "垃圾搜索",
          "pathName": "pages/indexs/search/search",
          "query": "",
          "scene": null,
          "partialCompile": {
            "enabled": true,
            "pages": []
          }
        },
        {
          "name": "搜索记录",
          "pathName": "pages/indexs/searchlog/searchlog",
          "query": "",
          "scene": null,
          "partialCompile": {
            "enabled": true,
            "pages": []
          }
        },
        {
          "name": "志愿通知",
          "pathName": "pages/mines/myrecruvoluns/myrecruvolun/myrecruvolun",
          "query": "",
          "scene": null,
          "partialCompile": {
            "enabled": true,
            "pages": []
          }
        }
      ]
    }
  }
}